<annotation><folder /><filename>q38_86_1_origin.png</filename><path>/content/drive/MyDrive/converted_to_xml/q38_86_1_origin.png</path><source><database /></source><size><width>808</width><height>571</height><depth>3</depth></size><segment>0</segment><object><name>Edge_Sparallel</name><pose>Unspecified</pose><truncated>0</truncated><difficult>0</difficult><bndbox><xmin>615</xmin><ymin>134</ymin><xmax>661</xmax><ymax>195</ymax></bndbox></object><object><name>Edge_Sparallel</name><pose>Unspecified</pose><truncated>0</truncated><difficult>0</difficult><bndbox><xmin>624</xmin><ymin>320</ymin><xmax>662</xmax><ymax>367</ymax></bndbox></object><object><name>Edge_Sparallel</name><pose>Unspecified</pose><truncated>0</truncated><difficult>0</difficult><bndbox><xmin>621</xmin><ymin>409</ymin><xmax>656</xmax><ymax>481</ymax></bndbox></object></annotation>